furlan_spellchecker/__about__.py
furlan_spellchecker/__init__.py
furlan_spellchecker/__main__.py
furlan_spellchecker/main.py
furlan_spellchecker/cli/__init__.py
furlan_spellchecker/cli/__main__.py
furlan_spellchecker/cli/app.py
furlan_spellchecker/cli/ascii_logo.py
furlan_spellchecker/cli/cof_protocol.py
furlan_spellchecker/cli/colors.py
furlan_spellchecker/cli/localization.py
furlan_spellchecker/cli/localization/en.json
furlan_spellchecker/cli/localization/fur.json
furlan_spellchecker/cli/localization/it.json
furlan_spellchecker/config/__init__.py
furlan_spellchecker/config/manager.py
furlan_spellchecker/config/schemas.py
furlan_spellchecker/core/__init__.py
furlan_spellchecker/core/exceptions.py
furlan_spellchecker/core/interfaces.py
furlan_spellchecker/core/types.py
furlan_spellchecker/database/__init__.py
furlan_spellchecker/database/downloader.py
furlan_spellchecker/database/elision.py
furlan_spellchecker/database/error.py
furlan_spellchecker/database/factory.py
furlan_spellchecker/database/frequency.py
furlan_spellchecker/database/interfaces.py
furlan_spellchecker/database/manager.py
furlan_spellchecker/database/phonetic.py
furlan_spellchecker/database/radix_tree.py
furlan_spellchecker/database/sqlite_database.py
furlan_spellchecker/database/user_dictionary.py
furlan_spellchecker/database/user_exceptions.py
furlan_spellchecker/database/repositories/__init__.py
furlan_spellchecker/database/repositories/base.py
furlan_spellchecker/database/repositories/cached.py
furlan_spellchecker/database/repositories/sqlite.py
furlan_spellchecker/dictionary/__init__.py
furlan_spellchecker/dictionary/dictionary.py
furlan_spellchecker/dictionary/radix_tree.py
furlan_spellchecker/entities/__init__.py
furlan_spellchecker/entities/processed_element.py
furlan_spellchecker/phonetic/__init__.py
furlan_spellchecker/phonetic/furlan_phonetic.py
furlan_spellchecker/services/__init__.py
furlan_spellchecker/services/dictionary_manager.py
furlan_spellchecker/services/io_service.py
furlanspellchecker-0.1.1.dist-info/METADATA
furlanspellchecker-0.1.1.dist-info/WHEEL
furlanspellchecker-0.1.1.dist-info/entry_points.txt
furlanspellchecker-0.1.1.dist-info/licenses/LICENSE
furlanspellchecker-0.1.1.dist-info/RECORD
