Metadata-Version: 2.4
Name: furlanspellchecker
Version: 0.1.1
Summary: A comprehensive spell checker for the Friulian language with CLI and pipeline service.
Project-URL: Homepage, https://github.com/daurmax/FurlanSpellChecker
Project-URL: Repository, https://github.com/daurmax/FurlanSpellChecker
Project-URL: Issues, https://github.com/daurmax/FurlanSpellChecker/issues
Project-URL: Documentation, https://github.com/daurmax/FurlanSpellChecker/blob/main/README.md
Author-email: Massimo Romanin <dev@massimoromanin.com>
License: Attribution-NonCommercial 4.0 International
License-File: LICENSE
Keywords: friulian,furlan,nlp,spellchecker,spelling,text-processing
Classifier: Development Status :: 3 - Alpha
Classifier: Intended Audience :: Developers
Classifier: Intended Audience :: Education
Classifier: License :: Other/Proprietary License
Classifier: Operating System :: OS Independent
Classifier: Programming Language :: Python :: 3
Classifier: Programming Language :: Python :: 3 :: Only
Classifier: Programming Language :: Python :: 3.10
Classifier: Programming Language :: Python :: 3.11
Classifier: Programming Language :: Python :: 3.12
Classifier: Topic :: Software Development :: Libraries :: Python Modules
Classifier: Topic :: Text Processing :: Linguistic
Requires-Python: >=3.10
Requires-Dist: click>=8.1.7
Requires-Dist: colorama>=0.4.6
Requires-Dist: msgpack>=1.0.0
Requires-Dist: rapidfuzz>=3.0.0
Requires-Dist: requests>=2.31.0
Provides-Extra: api
Requires-Dist: fastapi>=0.104.0; extra == 'api'
Requires-Dist: uvicorn>=0.24.0; extra == 'api'
Provides-Extra: dev
Requires-Dist: black>=24.4.0; extra == 'dev'
Requires-Dist: hypothesis>=6.0.0; extra == 'dev'
Requires-Dist: mypy>=1.10.0; extra == 'dev'
Requires-Dist: pytest-asyncio>=0.23.0; extra == 'dev'
Requires-Dist: pytest-cov>=4.1.0; extra == 'dev'
Requires-Dist: pytest>=8.0.0; extra == 'dev'
Requires-Dist: ruff>=0.5.0; extra == 'dev'
Requires-Dist: types-click>=7.1.8; extra == 'dev'
Requires-Dist: types-colorama>=0.4.15; extra == 'dev'
